pymscada/__init__.py
pymscada/__main__.py
pymscada/alarms.py
pymscada/bus_client.py
pymscada/bus_server.py
pymscada/callout.py
pymscada/checkout.py
pymscada/config.py
pymscada/console.py
pymscada/files.py
pymscada/history.py
pymscada/main.py
pymscada/misc.py
pymscada/module_config.py
pymscada/opnotes.py
pymscada/periodic.py
pymscada/protocol_constants.py
pymscada/samplers.py
pymscada/tag.py
pymscada/www_server.py
pymscada/demo/README.md
pymscada/demo/__init__.py
pymscada/demo/accuweather.yaml
pymscada/demo/alarms.yaml
pymscada/demo/bus.yaml
pymscada/demo/callout.yaml
pymscada/demo/files.yaml
pymscada/demo/history.yaml
pymscada/demo/logixclient.yaml
pymscada/demo/modbus_plc.py
pymscada/demo/modbusclient.yaml
pymscada/demo/modbusserver.yaml
pymscada/demo/openweather.yaml
pymscada/demo/opnotes.yaml
pymscada/demo/piapi.yaml
pymscada/demo/ping.yaml
pymscada/demo/pymscada-alarms.service
pymscada/demo/pymscada-bus.service
pymscada/demo/pymscada-callout.service
pymscada/demo/pymscada-demo-modbus_plc.service
pymscada/demo/pymscada-files.service
pymscada/demo/pymscada-history.service
pymscada/demo/pymscada-io-logixclient.service
pymscada/demo/pymscada-io-modbusclient.service
pymscada/demo/pymscada-io-modbusserver.service
pymscada/demo/pymscada-io-openweather.service
pymscada/demo/pymscada-io-piapi.service
pymscada/demo/pymscada-io-ping.service
pymscada/demo/pymscada-io-sms.service
pymscada/demo/pymscada-io-snmpclient.service
pymscada/demo/pymscada-io-witsapi.service
pymscada/demo/pymscada-opnotes.service
pymscada/demo/pymscada-wwwserver.service
pymscada/demo/sms.yaml
pymscada/demo/snmpclient.yaml
pymscada/demo/tags.yaml
pymscada/demo/witsapi.yaml
pymscada/demo/wwwserver.yaml
pymscada/demo/__pycache__/__init__.cpython-311.pyc
pymscada/iodrivers/__init__.py
pymscada/iodrivers/accuweather.py
pymscada/iodrivers/logix_client.py
pymscada/iodrivers/logix_map.py
pymscada/iodrivers/modbus_client.py
pymscada/iodrivers/modbus_map.py
pymscada/iodrivers/modbus_server.py
pymscada-0.2.5.dist-info/licenses/LICENSE
pymscada-0.2.5.dist-info/METADATA
pymscada-0.2.5.dist-info/WHEEL
pymscada-0.2.5.dist-info/entry_points.txt
pymscada-0.2.5.dist-info/top_level.txt
pymscada-0.2.5.dist-info/RECORD
