Metadata-Version: 2.4
Name: pymscada
Version: 0.2.5
Summary: Shared tag value SCADA with python backup and Angular UI
Author-email: Jamie Walton <jamie@walton.net.nz>
License: GPL-3.0-or-later
Project-URL: Homepage, https://github.com/jamie0walton/pymscada
Project-URL: Bug Tracker, https://github.com/jamie0walton/pymscada/issues
Classifier: Programming Language :: Python :: 3
Classifier: Programming Language :: JavaScript
Classifier: License :: OSI Approved :: GNU General Public License v3 (GPLv3)
Classifier: Operating System :: OS Independent
Classifier: Environment :: Console
Classifier: Development Status :: 1 - Planning
Requires-Python: >=3.9
License-File: LICENSE
Requires-Dist: PyYAML>=6.0.1
Requires-Dist: aiohttp>=3.8.5
Requires-Dist: pymscada-html>=0.2.2
Requires-Dist: cerberus>=1.3.5
Requires-Dist: pycomm3>=1.2.14
Requires-Dist: pysnmplib>=5.0.24
Dynamic: license-file
